PyCt6/__init__.py
PyCt6/appearance/__init__.py
PyCt6/appearance/mode_manager.py
PyCt6/appearance/theme_manager.py
PyCt6/widgets/__init__.py
PyCt6/widgets/c_button.py
PyCt6/widgets/c_combo_box.py
PyCt6/widgets/c_frame.py
PyCt6/widgets/c_label.py
PyCt6/widgets/c_line_edit.py
PyCt6/widgets/c_scrollable_frame.py
PyCt6/widgets/c_slider.py
PyCt6/widgets/c_text_edit.py
PyCt6/widgets/images/down_arrow.png
PyCt6/widgets/themes/blue.json
PyCt6/widgets/themes/green.json
PyCt6/widgets/themes/orange.json
PyCt6/widgets/themes/pink.json
PyCt6/widgets/themes/purple.json
PyCt6/widgets/themes/red.json
PyCt6/widgets/themes/yellow.json
PyCt6/windows/__init__.py
PyCt6/windows/c_main_window.py
PyCt6/windows/c_top_level.py
PyCt6/windows/images/logo.png
pyct6-6.0.6.dist-info/licenses/LICENSE
pyct6-6.0.6.dist-info/METADATA
pyct6-6.0.6.dist-info/WHEEL
pyct6-6.0.6.dist-info/top_level.txt
pyct6-6.0.6.dist-info/RECORD
