Metadata-Version: 2.4
Name: PyCt6
Version: 6.0.6
Summary: A modern and customizable python GUI interface library built from the PySide6 library
Home-page: https://github.com/Dliammc/CustomPyQt/
Author: D. Liam Mc.
Author-email: dliammc@duck.com
License: MIT License
Project-URL: Source, https://github.com/Dliammc/CustomPyQt
Classifier: Programming Language :: Python :: 3.9
Classifier: Programming Language :: Python :: 3.10
Classifier: Programming Language :: Python :: 3.11
Classifier: Programming Language :: Python :: 3.12
Classifier: Programming Language :: Python :: 3.13
Classifier: License :: OSI Approved :: MIT License
Classifier: Operating System :: OS Independent
Requires-Python: <3.14, >=3.9
License-File: LICENSE
Requires-Dist: PySide6
Dynamic: author
Dynamic: author-email
Dynamic: classifier
Dynamic: description
Dynamic: description-content-type
Dynamic: home-page
Dynamic: license
Dynamic: license-file
Dynamic: project-url
Dynamic: requires-dist
Dynamic: requires-python
Dynamic: summary
